[
    {
        "_id": "5fd66ce87ffed13e845915a9",
        "name": "hülkenberg",
        "jabatan": "konsul",
        "pangkat": "4c",
        "address": "frankfurt",
        "project" : "5fd7c1f3e0ecfb087a26b621"
    },
    {
        "_id": "5fd7c77e76716e0a3e8adcd2",
        "name": "max",
        "jabatan": "konsul",
        "pangkat": "1b",
        "address": "frankfurt",
        "project": "5fd7c205e0ecfb087a26b622"
    },
    {
        "_id": "5fd7c78b76716e0a3e8adcd3",
        "name": "lewis",
        "jabatan": "konsul",
        "pangkat": "3b",
        "address": "frankfurt",
        "project" :"5fd7c1f3e0ecfb087a26b621"
    },
    {
        "_id": "5fd7c79b76716e0a3e8adcd4",
        "name": "bottas",
        "jabatan": "protokol",
        "pangkat": "3b",
        "address": "frankfurt",
        "project":"5fd7c1f3e0ecfb087a26b621"
    },
    {
        "_id": "5fd7c7a376716e0a3e8adcd5",
        "name": "albon",
        "jabatan": "protokol",
        "pangkat": "3b",
        "address": "frankfurt",
        "project": "5fd7c205e0ecfb087a26b622"
    },
    {
        "_id": "5fd7c7b176716e0a3e8adcd6",
        "name": "sainz",
        "jabatan": "protokol",
        "pangkat": "3b",
        "address": "frankfurt",
        "project": "5fd7c20ce0ecfb087a26b623"
    },
    {
        "_id": "5fd7c7bb76716e0a3e8adcd7",
        "name": "norris",
        "jabatan": "protokol",
        "pangkat": "3b",
        "address": "frankfurt",
        "project": "5fd7c20ce0ecfb087a26b623"
    }
]